Metadata-Version: 2.1
Name: semantic-compare
Version: 0.9.0
Summary: NLP library that extracts, compares, transforms and sorts with buckets phrases.
Home-page: https://github.com/planeks-admin/NLP-spacy
Author: Planeks
Author-email: maxlytvynchuk@planeks.net
License: UNKNOWN
Platform: UNKNOWN
Classifier: Programming Language :: Python :: 3
Classifier: License :: OSI Approved :: MIT License
Classifier: Operating System :: OS Independent
Requires-Python: >=3.6
